LICENSE
README.md
setup.py
django_filter_autotools.egg-info/PKG-INFO
django_filter_autotools.egg-info/SOURCES.txt
django_filter_autotools.egg-info/dependency_links.txt
django_filter_autotools.egg-info/requires.txt
django_filter_autotools.egg-info/top_level.txt
django_filters_autotools/__init__.py
django_filters_autotools/mixins.py